molcomplib/__init__.py
molcomplib/molcomplib.py
molcomplib/bin/ecfp_3_2048_2d.pkl
molcomplib-1.1.3.dist-info/licenses/LICENSE
molcomplib-1.1.3.dist-info/METADATA
molcomplib-1.1.3.dist-info/WHEEL
molcomplib-1.1.3.dist-info/top_level.txt
molcomplib-1.1.3.dist-info/RECORD
