Metadata-Version: 2.4
Name: molcomplib
Version: 1.1.3
Summary: A library for the projection of chemical compounds onto 2D space, mostly for visualization purposes.
Home-page: https://github.com/sergsb/molcompview
Author: Sergey Sosnin
Author-email: sergey.sosnin@univie.ac.at
License: MIT
Keywords: chemistry,cheminformatics,t-SNE,visualization,chemical space
Classifier: Programming Language :: Python :: 3
Classifier: Programming Language :: Python :: 3.6
Classifier: License :: OSI Approved :: MIT License
Classifier: Operating System :: OS Independent
Classifier: Development Status :: 5 - Production/Stable
Classifier: Topic :: Scientific/Engineering :: Chemistry
Classifier: Intended Audience :: Science/Research
Requires-Python: >=3.6
License-File: LICENSE
Requires-Dist: rdkit
Requires-Dist: numpy
Dynamic: author
Dynamic: author-email
Dynamic: classifier
Dynamic: description
Dynamic: home-page
Dynamic: keywords
Dynamic: license
Dynamic: license-file
Dynamic: requires-dist
Dynamic: requires-python
Dynamic: summary
